linkdownloadersite/__init__.py
linkdownloadersite/linkdownloadersite.py
linkdownloadersite-0.1.2.dist-info/WHEEL
linkdownloadersite-0.1.2.dist-info/METADATA
linkdownloadersite-0.1.2.dist-info/RECORD
